{
  "id": "88eec459-6a0b-4acd-887f-af4c9f8ee3f4",
  "prevId": "00000000-0000-0000-0000-000000000000",
  "version": "7",
  "dialect": "postgresql",
  "tables": {
    "public.account": {
      "name": "account",
      "schema": "",
      "columns": {
        "id": {
          "name": "id",
          "type": "text",
          "primaryKey": true,
          "notNull": true
        },
        "accountId": {
          "name": "accountId",
          "type": "text",
          "primaryKey": false,
          "notNull": true
        },
        "providerId": {
          "name": "providerId",
          "type": "text",
          "primaryKey": false,
          "notNull": true
        },
        "userId": {
          "name": "userId",
          "type": "text",
          "primaryKey": false,
          "notNull": true
        },
        "accessToken": {
          "name": "accessToken",
          "type": "text",
          "primaryKey": false,
          "notNull": false
        },
        "refreshToken": {
          "name": "refreshToken",
          "type": "text",
          "primaryKey": false,
          "notNull": false
        },
        "idToken": {
          "name": "idToken",
          "type": "text",
          "primaryKey": false,
          "notNull": false
        },
        "accessTokenExpiresAt": {
          "name": "accessTokenExpiresAt",
          "type": "timestamp",
          "primaryKey": false,
          "notNull": false
        },
        "refreshTokenExpiresAt": {
          "name": "refreshTokenExpiresAt",
          "type": "timestamp",
          "primaryKey": false,
          "notNull": false
        },
        "scope": {
          "name": "scope",
          "type": "text",
          "primaryKey": false,
          "notNull": false
        },
        "password": {
          "name": "password",
          "type": "text",
          "primaryKey": false,
          "notNull": false
        },
        "createdAt": {
          "name": "createdAt",
          "type": "timestamp",
          "primaryKey": false,
          "notNull": false,
          "default": "now()"
        },
        "updatedAt": {
          "name": "updatedAt",
          "type": "timestamp",
          "primaryKey": false,
          "notNull": false,
          "default": "now()"
        }
      },
      "indexes": {},
      "foreignKeys": {
        "account_userId_user_id_fk": {
          "name": "account_userId_user_id_fk",
          "tableFrom": "account",
          "tableTo": "user",
          "columnsFrom": [
            "userId"
          ],
          "columnsTo": [
            "id"
          ],
          "onDelete": "no action",
          "onUpdate": "no action"
        }
      },
      "compositePrimaryKeys": {},
      "uniqueConstraints": {},
      "policies": {},
      "checkConstraints": {},
      "isRLSEnabled": true
    },
    "public.session": {
      "name": "session",
      "schema": "",
      "columns": {
        "id": {
          "name": "id",
          "type": "text",
          "primaryKey": true,
          "notNull": true
        },
        "expiresAt": {
          "name": "expiresAt",
          "type": "timestamp",
          "primaryKey": false,
          "notNull": true
        },
        "token": {
          "name": "token",
          "type": "text",
          "primaryKey": false,
          "notNull": true
        },
        "createdAt": {
          "name": "createdAt",
          "type": "timestamp",
          "primaryKey": false,
          "notNull": false,
          "default": "now()"
        },
        "updatedAt": {
          "name": "updatedAt",
          "type": "timestamp",
          "primaryKey": false,
          "notNull": false,
          "default": "now()"
        },
        "ipAddress": {
          "name": "ipAddress",
          "type": "text",
          "primaryKey": false,
          "notNull": false
        },
        "userAgent": {
          "name": "userAgent",
          "type": "text",
          "primaryKey": false,
          "notNull": false
        },
        "userId": {
          "name": "userId",
          "type": "text",
          "primaryKey": false,
          "notNull": true
        }
      },
      "indexes": {},
      "foreignKeys": {
        "session_userId_user_id_fk": {
          "name": "session_userId_user_id_fk",
          "tableFrom": "session",
          "tableTo": "user",
          "columnsFrom": [
            "userId"
          ],
          "columnsTo": [
            "id"
          ],
          "onDelete": "no action",
          "onUpdate": "no action"
        }
      },
      "compositePrimaryKeys": {},
      "uniqueConstraints": {
        "session_token_unique": {
          "name": "session_token_unique",
          "nullsNotDistinct": false,
          "columns": [
            "token"
          ]
        }
      },
      "policies": {},
      "checkConstraints": {},
      "isRLSEnabled": true
    },
    "public.user": {
      "name": "user",
      "schema": "",
      "columns": {
        "id": {
          "name": "id",
          "type": "text",
          "primaryKey": true,
          "notNull": true
        },
        "name": {
          "name": "name",
          "type": "text",
          "primaryKey": false,
          "notNull": true
        },
        "username": {
          "name": "username",
          "type": "text",
          "primaryKey": false,
          "notNull": false
        },
        "display_username": {
          "name": "display_username",
          "type": "text",
          "primaryKey": false,
          "notNull": false
        },
        "email": {
          "name": "email",
          "type": "text",
          "primaryKey": false,
          "notNull": true
        },
        "emailVerified": {
          "name": "emailVerified",
          "type": "boolean",
          "primaryKey": false,
          "notNull": true
        },
        "image": {
          "name": "image",
          "type": "text",
          "primaryKey": false,
          "notNull": false
        },
        "role": {
          "name": "role",
          "type": "text",
          "primaryKey": false,
          "notNull": true,
          "default": "'member'"
        },
        "gender": {
          "name": "gender",
          "type": "boolean",
          "primaryKey": false,
          "notNull": true
        },
        "xp": {
          "name": "xp",
          "type": "integer",
          "primaryKey": false,
          "notNull": true,
          "default": 0
        },
        "brain_level": {
          "name": "brain_level",
          "type": "integer",
          "primaryKey": false,
          "notNull": true,
          "default": 1
        },
        "energy_current": {
          "name": "energy_current",
          "type": "integer",
          "primaryKey": false,
          "notNull": true,
          "default": 5
        },
        "energy_last_updated": {
          "name": "energy_last_updated",
          "type": "timestamp",
          "primaryKey": false,
          "notNull": false,
          "default": "now()"
        },
        "unlimited_energy_until": {
          "name": "unlimited_energy_until",
          "type": "timestamp",
          "primaryKey": false,
          "notNull": false
        },
        "brain_stats": {
          "name": "brain_stats",
          "type": "jsonb",
          "primaryKey": false,
          "notNull": false,
          "default": "'{}'::jsonb"
        },
        "tutorial_status": {
          "name": "tutorial_status",
          "type": "jsonb",
          "primaryKey": false,
          "notNull": false,
          "default": "'{}'::jsonb"
        },
        "wechat_unionid": {
          "name": "wechat_unionid",
          "type": "text",
          "primaryKey": false,
          "notNull": false
        },
        "stripe_customer_id": {
          "name": "stripe_customer_id",
          "type": "text",
          "primaryKey": false,
          "notNull": false
        },
        "createdAt": {
          "name": "createdAt",
          "type": "timestamp",
          "primaryKey": false,
          "notNull": false,
          "default": "now()"
        },
        "updatedAt": {
          "name": "updatedAt",
          "type": "timestamp",
          "primaryKey": false,
          "notNull": false,
          "default": "now()"
        }
      },
      "indexes": {},
      "foreignKeys": {},
      "compositePrimaryKeys": {},
      "uniqueConstraints": {
        "user_username_unique": {
          "name": "user_username_unique",
          "nullsNotDistinct": false,
          "columns": [
            "username"
          ]
        },
        "user_email_unique": {
          "name": "user_email_unique",
          "nullsNotDistinct": false,
          "columns": [
            "email"
          ]
        },
        "user_wechat_unionid_unique": {
          "name": "user_wechat_unionid_unique",
          "nullsNotDistinct": false,
          "columns": [
            "wechat_unionid"
          ]
        }
      },
      "policies": {},
      "checkConstraints": {},
      "isRLSEnabled": true
    },
    "public.verification": {
      "name": "verification",
      "schema": "",
      "columns": {
        "id": {
          "name": "id",
          "type": "text",
          "primaryKey": true,
          "notNull": true
        },
        "identifier": {
          "name": "identifier",
          "type": "text",
          "primaryKey": false,
          "notNull": true
        },
        "value": {
          "name": "value",
          "type": "text",
          "primaryKey": false,
          "notNull": true
        },
        "expiresAt": {
          "name": "expiresAt",
          "type": "timestamp",
          "primaryKey": false,
          "notNull": true
        },
        "createdAt": {
          "name": "createdAt",
          "type": "timestamp",
          "primaryKey": false,
          "notNull": false,
          "default": "now()"
        },
        "updatedAt": {
          "name": "updatedAt",
          "type": "timestamp",
          "primaryKey": false,
          "notNull": false,
          "default": "now()"
        }
      },
      "indexes": {},
      "foreignKeys": {},
      "compositePrimaryKeys": {},
      "uniqueConstraints": {},
      "policies": {},
      "checkConstraints": {},
      "isRLSEnabled": true
    },
    "public.daily_activity": {
      "name": "daily_activity",
      "schema": "",
      "columns": {
        "id": {
          "name": "id",
          "type": "uuid",
          "primaryKey": true,
          "notNull": true,
          "default": "gen_random_uuid()"
        },
        "user_id": {
          "name": "user_id",
          "type": "text",
          "primaryKey": false,
          "notNull": true
        },
        "date": {
          "name": "date",
          "type": "date",
          "primaryKey": false,
          "notNull": true
        },
        "total_xp": {
          "name": "total_xp",
          "type": "integer",
          "primaryKey": false,
          "notNull": true,
          "default": 0
        },
        "sessions_count": {
          "name": "sessions_count",
          "type": "integer",
          "primaryKey": false,
          "notNull": true,
          "default": 0
        },
        "updated_at": {
          "name": "updated_at",
          "type": "timestamp",
          "primaryKey": false,
          "notNull": false,
          "default": "now()"
        }
      },
      "indexes": {},
      "foreignKeys": {
        "daily_activity_user_id_user_id_fk": {
          "name": "daily_activity_user_id_user_id_fk",
          "tableFrom": "daily_activity",
          "tableTo": "user",
          "columnsFrom": [
            "user_id"
          ],
          "columnsTo": [
            "id"
          ],
          "onDelete": "cascade",
          "onUpdate": "no action"
        }
      },
      "compositePrimaryKeys": {},
      "uniqueConstraints": {},
      "policies": {},
      "checkConstraints": {},
      "isRLSEnabled": false
    },
    "public.game_sessions": {
      "name": "game_sessions",
      "schema": "",
      "columns": {
        "id": {
          "name": "id",
          "type": "uuid",
          "primaryKey": true,
          "notNull": true,
          "default": "gen_random_uuid()"
        },
        "user_id": {
          "name": "user_id",
          "type": "text",
          "primaryKey": false,
          "notNull": true
        },
        "game_mode": {
          "name": "game_mode",
          "type": "text",
          "primaryKey": false,
          "notNull": true
        },
        "n_level": {
          "name": "n_level",
          "type": "integer",
          "primaryKey": false,
          "notNull": false
        },
        "score": {
          "name": "score",
          "type": "integer",
          "primaryKey": false,
          "notNull": true
        },
        "accuracy": {
          "name": "accuracy",
          "type": "integer",
          "primaryKey": false,
          "notNull": true
        },
        "config_snapshot": {
          "name": "config_snapshot",
          "type": "jsonb",
          "primaryKey": false,
          "notNull": true
        },
        "avg_reaction_time": {
          "name": "avg_reaction_time",
          "type": "integer",
          "primaryKey": false,
          "notNull": false
        },
        "created_at": {
          "name": "created_at",
          "type": "timestamp",
          "primaryKey": false,
          "notNull": true,
          "default": "now()"
        }
      },
      "indexes": {},
      "foreignKeys": {
        "game_sessions_user_id_user_id_fk": {
          "name": "game_sessions_user_id_user_id_fk",
          "tableFrom": "game_sessions",
          "tableTo": "user",
          "columnsFrom": [
            "user_id"
          ],
          "columnsTo": [
            "id"
          ],
          "onDelete": "cascade",
          "onUpdate": "no action"
        }
      },
      "compositePrimaryKeys": {},
      "uniqueConstraints": {},
      "policies": {},
      "checkConstraints": {},
      "isRLSEnabled": false
    },
    "public.user_unlocks": {
      "name": "user_unlocks",
      "schema": "",
      "columns": {
        "user_id": {
          "name": "user_id",
          "type": "text",
          "primaryKey": false,
          "notNull": true
        },
        "game_id": {
          "name": "game_id",
          "type": "text",
          "primaryKey": false,
          "notNull": true
        },
        "unlocked_params": {
          "name": "unlocked_params",
          "type": "jsonb",
          "primaryKey": false,
          "notNull": true,
          "default": "'{}'::jsonb"
        },
        "completed_level_ids": {
          "name": "completed_level_ids",
          "type": "integer[]",
          "primaryKey": false,
          "notNull": false
        },
        "updated_at": {
          "name": "updated_at",
          "type": "timestamp",
          "primaryKey": false,
          "notNull": false,
          "default": "now()"
        }
      },
      "indexes": {},
      "foreignKeys": {
        "user_unlocks_user_id_user_id_fk": {
          "name": "user_unlocks_user_id_user_id_fk",
          "tableFrom": "user_unlocks",
          "tableTo": "user",
          "columnsFrom": [
            "user_id"
          ],
          "columnsTo": [
            "id"
          ],
          "onDelete": "cascade",
          "onUpdate": "no action"
        }
      },
      "compositePrimaryKeys": {
        "user_unlocks_user_id_game_id_pk": {
          "name": "user_unlocks_user_id_game_id_pk",
          "columns": [
            "user_id",
            "game_id"
          ]
        }
      },
      "uniqueConstraints": {},
      "policies": {},
      "checkConstraints": {},
      "isRLSEnabled": false
    },
    "public.orders": {
      "name": "orders",
      "schema": "",
      "columns": {
        "id": {
          "name": "id",
          "type": "uuid",
          "primaryKey": true,
          "notNull": true,
          "default": "gen_random_uuid()"
        },
        "user_id": {
          "name": "user_id",
          "type": "text",
          "primaryKey": false,
          "notNull": true
        },
        "product_id": {
          "name": "product_id",
          "type": "text",
          "primaryKey": false,
          "notNull": false
        },
        "amount_paid": {
          "name": "amount_paid",
          "type": "integer",
          "primaryKey": false,
          "notNull": true
        },
        "currency": {
          "name": "currency",
          "type": "currency",
          "typeSchema": "public",
          "primaryKey": false,
          "notNull": true,
          "default": "'CNY'"
        },
        "status": {
          "name": "status",
          "type": "order_status",
          "typeSchema": "public",
          "primaryKey": false,
          "notNull": true,
          "default": "'created'"
        },
        "gateway_ref_id": {
          "name": "gateway_ref_id",
          "type": "text",
          "primaryKey": false,
          "notNull": false
        },
        "created_at": {
          "name": "created_at",
          "type": "timestamp",
          "primaryKey": false,
          "notNull": true,
          "default": "now()"
        },
        "paid_at": {
          "name": "paid_at",
          "type": "timestamp",
          "primaryKey": false,
          "notNull": false
        }
      },
      "indexes": {},
      "foreignKeys": {
        "orders_user_id_user_id_fk": {
          "name": "orders_user_id_user_id_fk",
          "tableFrom": "orders",
          "tableTo": "user",
          "columnsFrom": [
            "user_id"
          ],
          "columnsTo": [
            "id"
          ],
          "onDelete": "set null",
          "onUpdate": "no action"
        },
        "orders_product_id_products_id_fk": {
          "name": "orders_product_id_products_id_fk",
          "tableFrom": "orders",
          "tableTo": "products",
          "columnsFrom": [
            "product_id"
          ],
          "columnsTo": [
            "id"
          ],
          "onDelete": "no action",
          "onUpdate": "no action"
        }
      },
      "compositePrimaryKeys": {},
      "uniqueConstraints": {},
      "policies": {},
      "checkConstraints": {},
      "isRLSEnabled": false
    },
    "public.products": {
      "name": "products",
      "schema": "",
      "columns": {
        "id": {
          "name": "id",
          "type": "text",
          "primaryKey": true,
          "notNull": true
        },
        "type": {
          "name": "type",
          "type": "product_type",
          "typeSchema": "public",
          "primaryKey": false,
          "notNull": true
        },
        "price_cny": {
          "name": "price_cny",
          "type": "integer",
          "primaryKey": false,
          "notNull": true
        },
        "price_usd": {
          "name": "price_usd",
          "type": "integer",
          "primaryKey": false,
          "notNull": true
        },
        "rewards": {
          "name": "rewards",
          "type": "jsonb",
          "primaryKey": false,
          "notNull": true
        },
        "is_active": {
          "name": "is_active",
          "type": "integer",
          "primaryKey": false,
          "notNull": false,
          "default": 1
        }
      },
      "indexes": {},
      "foreignKeys": {},
      "compositePrimaryKeys": {},
      "uniqueConstraints": {},
      "policies": {},
      "checkConstraints": {},
      "isRLSEnabled": false
    },
    "public.games": {
      "name": "games",
      "schema": "",
      "columns": {
        "id": {
          "name": "id",
          "type": "text",
          "primaryKey": true,
          "notNull": true
        },
        "name_key": {
          "name": "name_key",
          "type": "text",
          "primaryKey": false,
          "notNull": true
        },
        "config_schema": {
          "name": "config_schema",
          "type": "jsonb",
          "primaryKey": false,
          "notNull": true
        },
        "is_active": {
          "name": "is_active",
          "type": "boolean",
          "primaryKey": false,
          "notNull": false,
          "default": true
        }
      },
      "indexes": {},
      "foreignKeys": {},
      "compositePrimaryKeys": {},
      "uniqueConstraints": {},
      "policies": {},
      "checkConstraints": {},
      "isRLSEnabled": false
    },
    "public.level_configs": {
      "name": "level_configs",
      "schema": "",
      "columns": {
        "id": {
          "name": "id",
          "type": "integer",
          "primaryKey": true,
          "notNull": true
        },
        "game_id": {
          "name": "game_id",
          "type": "text",
          "primaryKey": false,
          "notNull": true
        },
        "level_requirements": {
          "name": "level_requirements",
          "type": "jsonb",
          "primaryKey": false,
          "notNull": false
        },
        "unlock_criteria": {
          "name": "unlock_criteria",
          "type": "jsonb",
          "primaryKey": false,
          "notNull": false
        }
      },
      "indexes": {},
      "foreignKeys": {
        "level_configs_game_id_games_id_fk": {
          "name": "level_configs_game_id_games_id_fk",
          "tableFrom": "level_configs",
          "tableTo": "games",
          "columnsFrom": [
            "game_id"
          ],
          "columnsTo": [
            "id"
          ],
          "onDelete": "no action",
          "onUpdate": "no action"
        }
      },
      "compositePrimaryKeys": {},
      "uniqueConstraints": {},
      "policies": {},
      "checkConstraints": {},
      "isRLSEnabled": false
    }
  },
  "enums": {
    "public.currency": {
      "name": "currency",
      "schema": "public",
      "values": [
        "CNY",
        "USD"
      ]
    },
    "public.order_status": {
      "name": "order_status",
      "schema": "public",
      "values": [
        "created",
        "pending",
        "paid",
        "fulfilled",
        "failed",
        "refunded"
      ]
    },
    "public.product_type": {
      "name": "product_type",
      "schema": "public",
      "values": [
        "consumable",
        "subscription",
        "permanent"
      ]
    }
  },
  "schemas": {},
  "sequences": {},
  "roles": {},
  "policies": {},
  "views": {},
  "_meta": {
    "columns": {},
    "schemas": {},
    "tables": {}
  }
}